xxbait/__init__.py
xxbait/core/__init__.py
xxbait/core/module_installation.py
xxbait/core/options.py
xxbait/core/platform_selection.py
xxbait/core/reporting.py
xxbait/modules/__init__.py
xxbait/modules/browser_credentials.py
xxbait/modules/browser_history.py
xxbait/modules/cleanup.py
xxbait/modules/clipboard.py
xxbait/modules/desktop_tree.py
xxbait/modules/disclaimer.py
xxbait/modules/drive_info.py
xxbait/modules/file_finder.py
xxbait/modules/file_zipper.py
xxbait/modules/installed_programs.py
xxbait/modules/recent_files.py
xxbait/modules/shared_resources.py
xxbait/modules/system_info.py
xxbait/modules/users.py
xxbait/modules/wifi_credentials.py
xxbait/utils/__init__.py
xxbait/utils/decrypt.py
xxbait/utils/logger.py
xbait-1.0.0.dist-info/LICENSE
xbait-1.0.0.dist-info/METADATA
xbait-1.0.0.dist-info/WHEEL
xbait-1.0.0.dist-info/entry_points.txt
xbait-1.0.0.dist-info/top_level.txt
xbait-1.0.0.dist-info/RECORD
